ks_constants/__init__.py
ks_constants/devs.py
ks_constants/locale.py
ks_constants/map_switch.py
ks_constants/maps.py
ks_constants/ranks.py
ks_constants/regions.py
ks_constants/roles.py
tests/__init__.py
tests/basic_tests.py
ks_constants-1.2.75.dist-info/METADATA
ks_constants-1.2.75.dist-info/WHEEL
ks_constants-1.2.75.dist-info/top_level.txt
ks_constants-1.2.75.dist-info/RECORD
