Metadata-Version: 2.4
Name: KS_Constants
Version: 1.2.75
Summary: Contains constants defined for Kerrigan Survival 2
Home-page: https://github.com/kerrigan-survival-team/ks_constants_py
Author: Steven Su
Author-email: ks2devteam@gmail.com
License: MIT
Dynamic: author
Dynamic: author-email
Dynamic: description
Dynamic: description-content-type
Dynamic: home-page
Dynamic: license
Dynamic: summary
